pykitten/__init__.py
pykitten/audio/__init__.py
pykitten/audio/validators.py
pykitten-0.1.1.dist-info/LICENSE
pykitten-0.1.1.dist-info/METADATA
pykitten-0.1.1.dist-info/WHEEL
pykitten-0.1.1.dist-info/top_level.txt
pykitten-0.1.1.dist-info/RECORD
