Metadata-Version: 2.2
Name: pykitten
Version: 0.1.1
Summary: A versatile Python toolkit for various utilities
Home-page: https://github.com/grabim09/SnakeTools
Author: Agra Bima Yuda
Author-email: Agra Bima Yuda <agra.bima.ab@gmail.com>
License: MIT License
Project-URL: Homepage, https://github.com/grabim09/SnakeTools
Project-URL: Repository, https://github.com/grabim09/SnakeTools.git
Project-URL: Documentation, https://github.com/grabim09/SnakeTools#readme
Keywords: tools,utilities,audio,wav
Classifier: Development Status :: 3 - Alpha
Classifier: Intended Audience :: Developers
Classifier: License :: OSI Approved :: MIT License
Classifier: Programming Language :: Python :: 3
Classifier: Programming Language :: Python :: 3.7
Classifier: Programming Language :: Python :: 3.8
Classifier: Programming Language :: Python :: 3.9
Classifier: Programming Language :: Python :: 3.10
Requires-Python: >=3.7
License-File: LICENSE
Dynamic: author
Dynamic: home-page
Dynamic: requires-python
